CuckooAPI/__init__.py
cuckoo_modified_api-20160927.1.dist-info/DESCRIPTION.rst
cuckoo_modified_api-20160927.1.dist-info/METADATA
cuckoo_modified_api-20160927.1.dist-info/metadata.json
cuckoo_modified_api-20160927.1.dist-info/RECORD
cuckoo_modified_api-20160927.1.dist-info/top_level.txt
cuckoo_modified_api-20160927.1.dist-info/WHEEL
