Metadata-Version: 2.0
Name: cuckoo-modified-api
Version: 20160927.1
Summary: A Python library to interface with a cuckoo-modified instance
Home-page: https://github.com/keithjjones/cuckoo-modified-api
Author: Keith J. Jones
Author-email: keith@keithjjones.com
License: LICENSE
Platform: UNKNOWN
Requires-Dist: requests[security]
